mfd_connect/__init__.py
mfd_connect/base.py
mfd_connect/exceptions.py
mfd_connect/interactive_ssh.py
mfd_connect/local.py
mfd_connect/pxssh.py
mfd_connect/rpyc.py
mfd_connect/rpyc_zero_deploy.py
mfd_connect/serial.py
mfd_connect/sol.py
mfd_connect/ssh.py
mfd_connect/sshtunnel.py
mfd_connect/tunneled_rpyc.py
mfd_connect/tunneled_ssh.py
mfd_connect/winrm.py
mfd_connect/api/__init__.py
mfd_connect/api/download_utils.py
mfd_connect/pathlib/__init__.py
mfd_connect/pathlib/path.py
mfd_connect/process/__init__.py
mfd_connect/process/base.py
mfd_connect/process/interactive_ssh/__init__.py
mfd_connect/process/interactive_ssh/base.py
mfd_connect/process/local/__init__.py
mfd_connect/process/local/base.py
mfd_connect/process/local/posix.py
mfd_connect/process/local/windows.py
mfd_connect/process/rpyc/__init__.py
mfd_connect/process/rpyc/base.py
mfd_connect/process/rpyc/esxi.py
mfd_connect/process/rpyc/posix.py
mfd_connect/process/rpyc/windows.py
mfd_connect/process/ssh/__init__.py
mfd_connect/process/ssh/base.py
mfd_connect/process/ssh/esxi.py
mfd_connect/process/ssh/posix.py
mfd_connect/process/ssh/windows.py
mfd_connect/process/winrm/__init__.py
mfd_connect/process/winrm/base.py
mfd_connect/rpyc_server/__init__.py
mfd_connect/rpyc_server/__main__.py
mfd_connect/rpyc_server/rpyc_server.py
mfd_connect/telnet/__init__.py
mfd_connect/telnet/telnet.py
mfd_connect/telnet/telnet_console.py
mfd_connect/util/__init__.py
mfd_connect/util/ansiterm.py
mfd_connect/util/batch_queue.py
mfd_connect/util/connection_utils.py
mfd_connect/util/console_utils.py
mfd_connect/util/decorators.py
mfd_connect/util/pathlib_utils.py
mfd_connect/util/powershell_utils.py
mfd_connect/util/process_utils.py
mfd_connect/util/rpc_copy_utils.py
mfd_connect/util/rpc_permission_utils.py
mfd_connect/util/rpc_system_info_utils.py
mfd_connect/util/serial_utils.py
mfd_connect/util/deployment/__init__.py
mfd_connect/util/deployment/api.py
mfd_connect/util/deployment/python_deployment.py
mfd_connect-7.13.0.dist-info/licenses/AUTHORS.md
mfd_connect-7.13.0.dist-info/licenses/LICENSE.md
mfd_connect-7.13.0.dist-info/METADATA
mfd_connect-7.13.0.dist-info/WHEEL
mfd_connect-7.13.0.dist-info/top_level.txt
mfd_connect-7.13.0.dist-info/RECORD
