Metadata-Version: 2.4
Name: mfd-connect
Version: 7.13.0
Summary: Module for running commands on remote machine.
Project-URL: Homepage, https://github.com/intel/mfd
Project-URL: Repository, https://github.com/intel/mfd-connect
Project-URL: Issues, https://github.com/intel/mfd-connect/issues
Project-URL: Changelog, https://github.com/intel/mfd-connect/blob/main/CHANGELOG.md
Requires-Python: <3.14,>=3.10
License-File: LICENSE.md
License-File: AUTHORS.md
Requires-Dist: pexpect~=4.8.0
Requires-Dist: paramiko==3.4.0; platform_system != "VMkernel"
Requires-Dist: six
Requires-Dist: rpyc~=6.0.0
Requires-Dist: funcy~=1.14
Requires-Dist: scp~=0.13.4; platform_system != "VMkernel"
Requires-Dist: pywin32; sys_platform == "win32"
Requires-Dist: mfd-typing<2,>=1.23.0
Requires-Dist: mfd-common-libs>=1.11.0
Requires-Dist: psutil~=5.9.5; platform_system != "VMkernel"
Requires-Dist: mfd-ftp>=1.8.0
Requires-Dist: pywinrm~=0.4.3
Requires-Dist: netaddr
Requires-Dist: telnetlib-313-and-up; python_version >= "3.13"
Dynamic: license-file
